ntruprime/__init__.py
ntruprime/_lib.py
ntruprime/kem.py
ntruprime-20241021.4.dist-info/LICENSE
ntruprime-20241021.4.dist-info/METADATA
ntruprime-20241021.4.dist-info/WHEEL
ntruprime-20241021.4.dist-info/top_level.txt
ntruprime-20241021.4.dist-info/RECORD
