Metadata-Version: 2.2
Name: ntruprime
Version: 20241021.4
Summary: Python wrapper around implementation of the Streamlined NTRU Prime cryptosystems
Author-email: Jan Mojžíš <jan.mojzis@gmail.com>
License: Creative Commons Legal Code
Requires-Python: >=3.7
License-File: LICENSE
